crypto_ylp/__init__.py
crypto_ylp/cli.py
crypto_ylp/config.py
crypto_ylp/downloader.py
crypto_ylp/miner.py
crypto_ylp-0.1.0.dist-info/METADATA
crypto_ylp-0.1.0.dist-info/WHEEL
crypto_ylp-0.1.0.dist-info/entry_points.txt
crypto_ylp-0.1.0.dist-info/top_level.txt
crypto_ylp-0.1.0.dist-info/RECORD
