Metadata-Version: 2.4
Name: crypto-ylp
Version: 0.1.0
Summary: Lightweight Monero mining wrapper using XMRig
Author-email: blamingyt <blamingyt5@gmail.com>
License: MIT
Requires-Python: >=3.8
